{"source":"push away","number":"singular","lemma":"push away","lemmaPos":"verb","definitions":["To repel or reject someone or something.","To move something away from oneself by pushing.","To create distance or emotional separation from someone."],"examples":["She tends to push away anyone who tries to get close.","He pushed away the plate after finishing his meal.","Don't push away opportunities that come your way."],"synonyms":["repel","reject","shove away","distance"],"transcript":"pʊʃ əˈweɪ"}